llm_agent_protector-0.1.0.dist-info/licenses/LICENSE
llmagentprotector/__init__.py
llmagentprotector/config.py
llmagentprotector/polymorphic_prompt_assembler.py
llmagentprotector/setup.py
llm_agent_protector-0.1.0.dist-info/METADATA
llm_agent_protector-0.1.0.dist-info/WHEEL
llm_agent_protector-0.1.0.dist-info/top_level.txt
llm_agent_protector-0.1.0.dist-info/RECORD
