Metadata-Version: 2.4
Name: llm-agent-protector
Version: 0.1.0
Summary: Polymorphic Prompt Assembler to protect LLM agents from prompt injection and prompt leak
Author-email: Zhilong Wang <izhilongwang@gmail.com>
License-Expression: MIT
Project-URL: Homepage, https://github.com/zhilongwang/LLMAgentProtector
Project-URL: Repository, https://github.com/zhilongwang/LLMAgentProtector
Keywords: llm,prompt injection,agent,security,openai,protection
License-File: LICENSE
Dynamic: license-file
